soco_plugin/__init__.py
soco_plugin/gateway.py
soco_plugin/message.py
soco_plugin/command/__init__.py
soco_plugin/command/mode.py
soco_plugin/command/pause.py
soco_plugin/command/play.py
soco_plugin/command/playlist.py
soco_plugin/command/stop.py
soco_plugin/command/volume/__init__.py
soco_plugin/command/volume/absolute.py
soco_plugin/command/volume/ramp.py
soco_plugin/command/volume/relative.py
soco_plugin/tests/__init__.py
soco_plugin/tests/test_doctests.py
soco_plugin/tests/test_gateway.py
soco_plugin/trigger/__init__.py
soco_plugin/trigger/pause.py
soco_plugin/trigger/play.py
soco_plugin/trigger/stop.py
soco_plugin/trigger/volume.py
automate_sonos_plugin-0.9.1.dist-info/LICENSE
automate_sonos_plugin-0.9.1.dist-info/METADATA
automate_sonos_plugin-0.9.1.dist-info/WHEEL
automate_sonos_plugin-0.9.1.dist-info/top_level.txt
automate_sonos_plugin-0.9.1.dist-info/RECORD
